vyperdatum/__init__.py
vyperdatum/db.py
vyperdatum/enums.py
vyperdatum/logging_conf.json
vyperdatum/pipeline.py
vyperdatum/transformer.py
vyperdatum/assets/vdatum/AKglacier00_8301/AKglacier00_8301.kml
vyperdatum/assets/vdatum/AKwhale00_8301/AKwhale00_8301.kml
vyperdatum/assets/vdatum/AKyakutat00_8301/AKyakutat00_8301.kml
vyperdatum/assets/vdatum/ALFLgom02_8301/ALFLgom02_8301.kml
vyperdatum/assets/vdatum/ALmobile02_8301/ALmobile02_8301.kml
vyperdatum/assets/vdatum/CAmontby13_8301/CAmontby13_8301.kml
vyperdatum/assets/vdatum/CAoregon00_8301/CAoregon00_8301.kml
vyperdatum/assets/vdatum/CAsfbay13_8301/CAsfbay13_8301.kml
vyperdatum/assets/vdatum/CAsfdel00_8301/CAsfdel00_8301.kml
vyperdatum/assets/vdatum/CAsouin00_8301/CAsouin00_8301.kml
vyperdatum/assets/vdatum/CAsouthn00_8301/CAsouthn00_8301.kml
vyperdatum/assets/vdatum/CRD/CRD.kml
vyperdatum/assets/vdatum/DEVAemb23_8301/DEVAemb23_8301.kml
vyperdatum/assets/vdatum/DEdelbay33_8301/DEdelbay33_8301.kml
vyperdatum/assets/vdatum/FLGAeastbays31_8301/FLGAeastbays31_8301.kml
vyperdatum/assets/vdatum/FLGAeastshelf41_8301/FLGAeastshelf41_8301.kml
vyperdatum/assets/vdatum/FLandrew02_8301/FLandrew02_8301.kml
vyperdatum/assets/vdatum/FLapalach01_8301/FLapalach01_8301.kml
vyperdatum/assets/vdatum/FLjoseph03_8301/FLjoseph03_8301.kml
vyperdatum/assets/vdatum/FLpensac02_8301/FLpensac02_8301.kml
vyperdatum/assets/vdatum/FLsoicw01_8301/FLsoicw01_8301.kml
vyperdatum/assets/vdatum/FLsouth12_8301/FLsouth12_8301.kml
vyperdatum/assets/vdatum/FLwest01_8301/FLwest01_8301.kml
vyperdatum/assets/vdatum/GASCNCsab31_8301/GASCNCsab31_8301.kml
vyperdatum/assets/vdatum/LATXwest01_8301/LATXwest01_8301.kml
vyperdatum/assets/vdatum/LAmobile02_8301/LAmobile02_8301.kml
vyperdatum/assets/vdatum/MDVAechb11_8301/MDVAechb11_8301.kml
vyperdatum/assets/vdatum/MDnwchb11_8301/MDnwchb11_8301.kml
vyperdatum/assets/vdatum/MENHMAgome23_8301/MENHMAgome23_8301.kml
vyperdatum/assets/vdatum/NCcoast11_8301/NCcoast11_8301.kml
vyperdatum-0.3.42.dist-info/licenses/LICENSE
vyperdatum-0.3.42.dist-info/METADATA
vyperdatum-0.3.42.dist-info/WHEEL
vyperdatum-0.3.42.dist-info/top_level.txt
vyperdatum-0.3.42.dist-info/RECORD
