Metadata-Version: 2.4
Name: vyperdatum
Version: 0.3.42
Summary: Vyperdatum with built-in regional datums, proj.db, and vdatum vector files.
Author-email: Mohammad Ashkezari <mohammad.ashkezari@noaa.gov>
License: Creative Commons Legal Code
Project-URL: Documentation, https://vyperdatum.readthedocs.io/en/latest/
Project-URL: Repository, https://github.com/mohammadashkezari-noaa/vyperdatum
Keywords: bathymetry,datum,NOAA,NBS
Classifier: Development Status :: 3 - Alpha
Classifier: Programming Language :: Python
Requires-Python: >=3.8
License-File: LICENSE
Requires-Dist: numpy
Requires-Dist: pyarrow
Requires-Dist: pyproj
Requires-Dist: pandas
Requires-Dist: geopandas
Requires-Dist: tqdm
Requires-Dist: colorama
Requires-Dist: pydantic
Requires-Dist: networkx
Requires-Dist: h5py
Requires-Dist: lxml
Requires-Dist: requests
Requires-Dist: laspy
Requires-Dist: shapely
Provides-Extra: tests
Requires-Dist: pytest; extra == "tests"
Requires-Dist: pytest-cov; extra == "tests"
Provides-Extra: lint
Requires-Dist: flake8; extra == "lint"
Requires-Dist: black; extra == "lint"
Provides-Extra: docs
Requires-Dist: sphinx; extra == "docs"
Requires-Dist: sphinx-rtd-theme; extra == "docs"
Dynamic: license-file
